ial_build/__init__.py
ial_build/algos.py
ial_build/bundle.py
ial_build/config.py
ial_build/repositories.py
ial_build/util.py
ial_build/cli/__init__.py
ial_build/cli/bundle2pack.py
ial_build/cli/find_bundle.py
ial_build/cli/fork_point.py
ial_build/cli/get_bundle.py
ial_build/cli/git2pack.py
ial_build/cli/ial2pack.py
ial_build/conf/gmkpack/sources_filters/IAL-CY48T1.txt
ial_build/conf/gmkpack/sources_filters/IAL-CY48T2.txt
ial_build/conf/gmkpack/sources_filters/IAL-CY48T3_mrg48R1.01.txt
ial_build/conf/gmkpack/sources_filters/IAL-CY48T3_mrg48R1.03.txt
ial_build/conf/gmkpack/sources_filters/IAL-CY49.txt
ial_build/conf/gmkpack/sources_filters/IAL-CY50.txt
ial_build/conf/gmkpack/sources_filters/IAL.txt
ial_build/conf/gmkpack/sources_filters/oops.txt
ial_build/conf/gmkpack/sources_filters/phyex.txt
ial_build/pygmkpack/__init__.py
ial_build/pygmkpack/gmkpack.py
ial_build/pygmkpack/pack.py
ial_build-1.4.7.dist-info/licenses/LICENSE
ial_build-1.4.7.dist-info/METADATA
ial_build-1.4.7.dist-info/WHEEL
ial_build-1.4.7.dist-info/entry_points.txt
ial_build-1.4.7.dist-info/top_level.txt
ial_build-1.4.7.dist-info/RECORD
