Metadata-Version: 2.4
Name: ial_build
Version: 1.4.7
Summary: IAL-build: Tools for Source Code Management and build of IAL code.
Author-email: Alexandre Mary <alexandre.mary@meteo.fr>
License: CECILL-C
Project-URL: source, https://github.com/ACCORD-NWP/IAL-build.git
Project-URL: tracker, https://github.com/ACCORD-NWP/IAL-build/issues
Requires-Python: >=3.10
License-File: LICENSE
Requires-Dist: ecbundle>=2.4.0
Dynamic: license-file
